Metadata-Version: 2.1
Name: nortec
Version: 0.3
Summary: A Python package for retrieving data from Nortec/Evaskeri backend
Home-page: https://github.com/kasperkls02/nortec
Author: Kasper Læssø Sørensen
Author-email: kasper@laessoerensen.dk
Classifier: Programming Language :: Python :: 3
Classifier: License :: OSI Approved :: MIT License
